catchmeifyoucan/__init__.py
catchmeifyoucan-0.0.1.dist-info/METADATA
catchmeifyoucan-0.0.1.dist-info/WHEEL
catchmeifyoucan-0.0.1.dist-info/top_level.txt
catchmeifyoucan-0.0.1.dist-info/RECORD
