Metadata-Version: 2.4
Name: catchmeifyoucan
Version: 0.0.1
Summary: PLACEHOLDER: Google Cloud Fraud Detection SDK - Coming Soon
Home-page: 
Author: Subhadip Mitra, Archanaa Ravikumar, Kerrie Hudson
Author-email: subhadipmitra@google.com
Classifier: Development Status :: 1 - Planning
Classifier: Intended Audience :: Developers
Classifier: License :: Other/Proprietary License
Classifier: Programming Language :: Python :: 3
Classifier: Programming Language :: Python :: 3.8
Classifier: Programming Language :: Python :: 3.9
Classifier: Programming Language :: Python :: 3.10
Classifier: Programming Language :: Python :: 3.11
Requires-Python: >=3.8
Dynamic: author
Dynamic: author-email
Dynamic: classifier
Dynamic: description
Dynamic: description-content-type
Dynamic: requires-python
Dynamic: summary
